piimasking/__init__.py
piimasking/masking_pipeline.py
piimasking-0.0.4.dist-info/LICENSE
piimasking-0.0.4.dist-info/METADATA
piimasking-0.0.4.dist-info/WHEEL
piimasking-0.0.4.dist-info/top_level.txt
piimasking-0.0.4.dist-info/RECORD
