Metadata-Version: 2.1
Name: piimasking
Version: 0.0.4
Summary: This repository contains a Python program designed to execute Pii Masking
Home-page: 
Author: Amaan Patel
Author-email: amaanpatel7868@gmail.com
Classifier: Programming Language :: Python :: 3
Classifier: License :: OSI Approved :: MIT License
Classifier: Operating System :: OS Independent
Requires-Python: >=3.7
License-File: LICENSE
Requires-Dist: presidio-anonymizer
Requires-Dist: presidio-analyzer
Requires-Dist: spacy
Requires-Dist: gliner-spacy
Requires-Dist: azure-data-tables
